dashmcp/__init__.py
dashmcp/config_loader.py
dashmcp/server.py
dashmcp/config/docsets/actionscript.yaml
dashmcp/config/docsets/akka.yaml
dashmcp/config/docsets/angular.yaml
dashmcp/config/docsets/angularjs.yaml
dashmcp/config/docsets/ansible.yaml
dashmcp/config/docsets/apache_http_server.yaml
dashmcp/config/docsets/apple_api_reference.yaml
dashmcp/config/docsets/applescript.yaml
dashmcp/config/docsets/arduino.yaml
dashmcp/config/docsets/backbonejs.yaml
dashmcp/config/docsets/bash.yaml
dashmcp/config/docsets/boost.yaml
dashmcp/config/docsets/bootstrap2.yaml
dashmcp/config/docsets/bootstrap3.yaml
dashmcp/config/docsets/bootstrap4.yaml
dashmcp/config/docsets/bootstrap5.yaml
dashmcp/config/docsets/bourbon.yaml
dashmcp/config/docsets/c.yaml
dashmcp/config/docsets/cappuccino.yaml
dashmcp/config/docsets/chai.yaml
dashmcp/config/docsets/clojure.yaml
dashmcp/config/docsets/cmake.yaml
dashmcp/config/docsets/cocos2d.yaml
dashmcp/config/docsets/cocos2d_x.yaml
dashmcp/config/docsets/cocos3d.yaml
dashmcp/config/docsets/codeigniter.yaml
dashmcp/config/docsets/coffeescript.yaml
dashmcp/config/docsets/coldfusion.yaml
dashmcp/config/docsets/common_lisp.yaml
dashmcp/config/docsets/compass.yaml
dashmcp/config/docsets/couchdb.yaml
dashmcp/config/docsets/cpp.yaml
dashmcp/config/docsets/css.yaml
dashmcp/config/docsets/d3js.yaml
dashmcp/config/docsets/dart.yaml
dashmcp/config/docsets/django.yaml
dashmcp/config/docsets/docker.yaml
dashmcp/config/docsets/doctrine_orm.yaml
dashmcp/config/docsets/dojo.yaml
dashmcp/config/docsets/drupal.yaml
dashmcp/config/docsets/elasticsearch.yaml
dashmcp/config/docsets/elixir.yaml
dashmcp/config/docsets/emacs_lisp.yaml
dashmcp/config/docsets/emberjs.yaml
dashmcp/config/docsets/emmet.yaml
dashmcp/config/docsets/erlang.yaml
dashmcp/config/docsets/express.yaml
dashmcp/config/docsets/extjs.yaml
dashmcp/config/docsets/flask.yaml
dashmcp/config/docsets/font_awesome.yaml
dashmcp/config/docsets/foundation.yaml
dashmcp/config/docsets/go.yaml
dashmcp-0.1.1.dist-info/METADATA
dashmcp-0.1.1.dist-info/WHEEL
dashmcp-0.1.1.dist-info/entry_points.txt
dashmcp-0.1.1.dist-info/top_level.txt
dashmcp-0.1.1.dist-info/RECORD
