Metadata-Version: 2.4
Name: dashmcp
Version: 0.1.1
Summary: Search local documentation from Dash through MCP
Home-page: https://github.com/codybrom/dashmcp
Author: Cody Bromley
Author-email: dev@codybrom.com
Project-URL: Bug Reports, https://github.com/codybrom/dashmcp/issues
Project-URL: Source, https://github.com/codybrom/dashmcp
Keywords: mcp model-context-protocol dash documentation llm
Classifier: Development Status :: 3 - Alpha
Classifier: Intended Audience :: Developers
Classifier: License :: OSI Approved :: MIT License
Classifier: Operating System :: MacOS
Classifier: Programming Language :: Python :: 3
Classifier: Programming Language :: Python :: 3.8
Classifier: Programming Language :: Python :: 3.9
Classifier: Programming Language :: Python :: 3.10
Classifier: Programming Language :: Python :: 3.11
Classifier: Programming Language :: Python :: 3.12
Classifier: Topic :: Software Development :: Documentation
Classifier: Topic :: Utilities
Requires-Python: >=3.8
Requires-Dist: mcp>=0.1.0
Requires-Dist: brotli>=1.0.0
Requires-Dist: pytest>=7.0.0
Requires-Dist: pytest-cov>=4.0.0
Requires-Dist: pytest-xdist>=3.0.0
Requires-Dist: pre-commit>=3.5.0
Requires-Dist: yamlfix>=1.16.0
Requires-Dist: black>=23.12.1
Requires-Dist: flake8>=7.0.0
Dynamic: author
Dynamic: author-email
Dynamic: classifier
Dynamic: description
Dynamic: description-content-type
Dynamic: home-page
Dynamic: keywords
Dynamic: project-url
Dynamic: requires-dist
Dynamic: requires-python
Dynamic: summary
